.travis.yml
AUTHORS
ChangeLog
LICENSE
README.rst
requirements.txt
setup.cfg
setup.py
test-requirements.txt
tox.ini
pymongomodem/__init__.py
pymongomodem/utils.py
python_pymongomodem.egg-info/PKG-INFO
python_pymongomodem.egg-info/SOURCES.txt
python_pymongomodem.egg-info/dependency_links.txt
python_pymongomodem.egg-info/not-zip-safe
python_pymongomodem.egg-info/pbr.json
python_pymongomodem.egg-info/top_level.txt
tests/__init__.py
tests/pymongomodem_test.py