Metadata-Version: 1.1
Name: python-pymongomodem
Version: 0.0.3
Summary: python method to deal with pymongo cringing around key with dots
Home-page: UNKNOWN
Author: Internap
Author-email: opensource@internap.com
License: UNKNOWN
Platform: UNKNOWN
Classifier: Development Status :: 5 - Production/Stable
Classifier: Intended Audience :: Developers
Classifier: License :: OSI Approved :: Apache Software License
Classifier: Operating System :: POSIX
Classifier: Programming Language :: Python :: 2.7
